entity_gym/__init__.py
entity_gym/dataclass_utils.py
entity_gym/env/__init__.py
entity_gym/env/action.py
entity_gym/env/add_metrics_wrapper.py
entity_gym/env/common.py
entity_gym/env/env_list.py
entity_gym/env/environment.py
entity_gym/env/parallel_env_list.py
entity_gym/env/validator.py
entity_gym/env/vec_env.py
entity_gym/examples/__init__.py
entity_gym/examples/cherry_pick.py
entity_gym/examples/count.py
entity_gym/examples/floor_is_lava.py
entity_gym/examples/minefield.py
entity_gym/examples/minesweeper.py
entity_gym/examples/move_to_origin.py
entity_gym/examples/multi_armed_bandit.py
entity_gym/examples/multi_snake.py
entity_gym/examples/not_hotdog.py
entity_gym/examples/pick_matching_balls.py
entity_gym/examples/rock_paper_scissors.py
entity_gym/examples/tutorial.py
entity_gym/examples/xor.py
entity_gym/main.py
entity_gym/py.typed
entity_gym/ragged_dict.py
entity_gym/runner.py
entity_gym/serialization/__init__.py
entity_gym/serialization/msgpack_ragged.py
entity_gym/serialization/sample_loader.py
entity_gym/serialization/sample_recorder.py
entity_gym/simple_trace.py
entity_gym/tests/test_environment.py
entity_gym/tests/test_sample_recorder.py
entity_gym/tests/test_validator.py
entity_gym-0.1.10.dist-info/METADATA
entity_gym-0.1.10.dist-info/WHEEL
entity_gym-0.1.10.dist-info/RECORD
