Metadata-Version: 2.1
Name: entity-gym
Version: 0.1.10
Summary: Entity Gym
License: MIT
Author: Clemens Winter
Author-email: clemenswinter1@gmail.com
Requires-Python: >=3.7.1,<3.11
Classifier: License :: OSI Approved :: Apache Software License
Classifier: License :: OSI Approved :: MIT License
Classifier: Programming Language :: Python :: 3
Classifier: Programming Language :: Python :: 3.8
Classifier: Programming Language :: Python :: 3.9
Classifier: Programming Language :: Python :: 3.10
Classifier: Topic :: Scientific/Engineering :: Artificial Intelligence
Requires-Dist: click (>=8.1.3,<9.0.0)
Requires-Dist: cloudpickle (>=2.0.0,<3.0.0)
Requires-Dist: msgpack (>=1.0.3,<2.0.0)
Requires-Dist: msgpack-numpy (>=0.4.7,<0.5.0)
Requires-Dist: ragged-buffer (>=0.4.3,<0.5.0)
Requires-Dist: tqdm (>=4.63.1,<5.0.0)
